s3_client_lib/s3_client
s3_client_lib/s3_client.py
s3_client_lib/s3_multipart_client.py
s3_client_lib/tmp
s3_client_lib/utils.py
s3_client_lib-0.2.2.dist-info/WHEEL
s3_client_lib-0.2.2.dist-info/METADATA
s3_client_lib-0.2.2.dist-info/RECORD
