Metadata-Version: 2.1
Name: s3-client-lib
Version: 0.2.2
Summary: S3 client lib
Author: Radim Spigel
Author-email: spigel@cesnet.cz
Requires-Python: >=3.6,<4.0
Classifier: Programming Language :: Python :: 3
Classifier: Programming Language :: Python :: 3.6
Classifier: Programming Language :: Python :: 3.7
Classifier: Programming Language :: Python :: 3.8
Classifier: Programming Language :: Python :: 3.9
Classifier: Programming Language :: Python :: 3.10
Classifier: Programming Language :: Python :: 3.11
Requires-Dist: boto3 (>=1.14.18,<2.0.0)
